lerl/__init__.py
lerl/policies.py
lerl/qan.py
lerl/qkr.py
lerl/qrl.py
lerl/qrl2.py
lerl/qsp.py
lerl/qsp2.py
lerl/utils.py
lerl-0.9.0.dist-info/licenses/LICENSE
lerl-0.9.0.dist-info/METADATA
lerl-0.9.0.dist-info/WHEEL
lerl-0.9.0.dist-info/top_level.txt
lerl-0.9.0.dist-info/RECORD
