Metadata-Version: 2.4
Name: lerl
Version: 0.9.0
Summary: Multi code-snippet generator for notebooks
Author-email: Hammad Ihsan <hammadihsan558@gmail.com>
License-File: LICENSE
Requires-Dist: numpy
Requires-Dist: ipython
Dynamic: license-file
